setup.py
plk345_distributions/Binomialdistribution.py
plk345_distributions/Gaussiandistribution.py
plk345_distributions/Generaldistribution.py
plk345_distributions/__init__.py
plk345_distributions.egg-info/PKG-INFO
plk345_distributions.egg-info/SOURCES.txt
plk345_distributions.egg-info/dependency_links.txt
plk345_distributions.egg-info/not-zip-safe
plk345_distributions.egg-info/top_level.txt