Metadata-Version: 1.0
Name: plk345-distributions
Version: 2.6
Summary: Gaussian distributions
Home-page: UNKNOWN
Author: Irving Chow
Author-email: 1624000827@qq.com
License: UNKNOWN
Platform: UNKNOWN
